vnfaker/__init__.py
vnfaker/commonUtils.py
vnfaker/generator.py
vnfaker/data/__init__.py
vnfaker/data/company/__init__.py
vnfaker/data/company/company.name
vnfaker/data/occupation/__init__.py
vnfaker/data/occupation/occupation.name
vnfaker/data/person/__init__.py
vnfaker/data/person/female.name
vnfaker/data/person/female_middle.name
vnfaker/data/person/first.name
vnfaker/data/person/last.name
vnfaker/data/person/male.name
vnfaker/data/person/male_middle.name
vnfaker/data/person/religion.name
vnfaker/data/provinces/__init__.py
vnfaker/data/provinces/flat-divisions.json
vnfaker/data/provinces/nested-divisions.json
vnfaker/data/religion/__init__.py
vnfaker/data/religion/religion.name
vnfaker/data/sentence/__init__.py
vnfaker/data/sentence/sentence.txt
vnfaker-0.0.5.dist-info/LICENSE.txt
vnfaker-0.0.5.dist-info/METADATA
vnfaker-0.0.5.dist-info/WHEEL
vnfaker-0.0.5.dist-info/top_level.txt
vnfaker-0.0.5.dist-info/RECORD
