Metadata-Version: 2.1
Name: vnfaker
Version: 0.0.5
Summary: vnfaker is a Python package that generates fake data about fullname, address, phone, date_of_birth,... in Viet Nam.
Home-page: https://github.com/phanducquang/vnfaker
Author: Phan Duc Quang
Author-email: phanducquang07@gmail.com
License: UNKNOWN
Project-URL: Bug Tracker, https://github.com/phanducquang/vnfaker/issues
Platform: UNKNOWN
Classifier: Programming Language :: Python :: 3
Classifier: License :: OSI Approved :: MIT License
Classifier: Operating System :: OS Independent
Requires-Python: >=3.7
License-File: LICENSE.txt
Requires-Dist: orjson (>=3.8.10)
Requires-Dist: unidecode (>=1.3.6)
